mlx/sdk/core/__init__.py
mlx/sdk/core/auth.py
mlx/sdk/core/base.py
mlx/sdk/core/config.py
mlx/sdk/core/errors.py
mlx/sdk/core/util.py
mlx/sdk/core/version.py
ncloud_mlx_sdk-0.1.1.dist-info/METADATA
ncloud_mlx_sdk-0.1.1.dist-info/WHEEL
ncloud_mlx_sdk-0.1.1.dist-info/licenses/LICENSE
ncloud_mlx_sdk-0.1.1.dist-info/RECORD
