Metadata-Version: 2.4
Name: ncloud-mlx-sdk
Version: 0.1.1
Summary: SDK for the ML expert Platform on NAVER Cloud Platform
Project-URL: Homepage, https://guide.ncloud-docs.com/docs/ai-mlxp-overview
Project-URL: Documentation, https://guide.ncloud-docs.com/docs/ai-mlxp-overview
Author-email: navercloud-mlxp <dl_mlx_ncp_dev@navercorp.com>
License-Expression: Apache-2.0
License-File: LICENSE
Requires-Python: <4.0.0,>=3.9.0
Requires-Dist: aiofiles<24,>=23.2.1
Requires-Dist: google-auth-oauthlib<2,>=1.2.0
Requires-Dist: httpx<0.28,>=0.27.0
Requires-Dist: kubeconfig<2,>=1.1.1
Requires-Dist: kubernetes<28,>=27.2.0
Requires-Dist: pydantic<3,>=2.7.4
Requires-Dist: pyjwt<3,>=2.8.0
Requires-Dist: python-dateutil<3,>=2.9.0.post0
Requires-Dist: pyyaml<7,>=6.0.1
Requires-Dist: requests<3,>=2.32.3
Requires-Dist: six<2,>=1.16.0
Requires-Dist: timeago<2,>=1.0.16
Requires-Dist: typing==3.7.4.3
Requires-Dist: yamlpath<4,>=3.8.2
